{
  "project_info": {
    "project_number": "507920478318",
    "project_id": "fir-todo-1c513",
    "storage_bucket": "fir-todo-1c513.appspot.com"
  },
  "client": [
    {
      "client_info": {
        "mobilesdk_app_id": "1:507920478318:android:2bf946ddf5e4ca52d7f67f",
        "android_client_info": {
          "package_name": "com.example.firebase_todo_app"
        }
      },
      "oauth_client": [
        {
          "client_id": "507920478318-brhlkbt5kq90j3s5r4fmc3df6ql8hrd5.apps.googleusercontent.com",
          "client_type": 3
        }
      ],
      "api_key": [
        {
          "current_key": "AIzaSyCxlmbZhCX6HJm7VCiFOEijPYAKawanC-A"
        }
      ],
      "services": {
        "appinvite_service": {
          "other_platform_oauth_client": [
            {
              "client_id": "507920478318-brhlkbt5kq90j3s5r4fmc3df6ql8hrd5.apps.googleusercontent.com",
              "client_type": 3
            }
          ]
        }
      }
    }
  ],
  "configuration_version": "1"
}